{
  "name": "Синонимы — прил. и сущ.",
  "category": "синонимы",
  "cards": [
    { "ru": "счастливый (чувство) — как отличить от lucky?", "en": "happy = чувство; lucky = повезло" },
    { "ru": "простой (несложно) — как отличить от light?", "en": "easy = несложно; light = лёгкий по весу" },
    { "ru": "высокий (человек) — как отличить от high?", "en": "tall = люди/здания; high = уровень/высота" },
    { "ru": "трудный — как отличить от hardly?", "en": "hard = трудный; hardly = едва, почти нет" },
    { "ru": "интересный (объект) — как отличить от interested?", "en": "interesting = объект; interested = эмоция" },
    { "ru": "захватывающий — как отличить от excited?", "en": "exciting = объект; excited = эмоция" },
    { "ru": "пустой — как отличить от free, vacant, spare?", "en": "empty = без содержимого; free = свободно; vacant = место; spare = запасной" },
    { "ru": "как (похоже) — как отличить от as?", "en": "like = похоже; as = в роли" },
    { "ru": "тоже (в отрицаниях) — как отличить от too и also?", "en": "either = в отрицаниях; too = в конце; also = в начале" },
    { "ru": "всё ещё — как отличить от yet и already?", "en": "still = всё ещё; yet = в вопросах/отрицаниях; already = уже" },
    { "ru": "поздно — как отличить от lately и latest?", "en": "late = поздно; lately = недавно; latest = самый последний" },
    { "ru": "кроме (исключает) — как отличить от besides?", "en": "except = исключает; besides = добавляет" },
    { "ru": "среди (группа) — как отличить от between?", "en": "among = группа; between = между двумя" },
    { "ru": "пара предметов — как отличить от couple?", "en": "pair = предметы; couple = чаще люди" },
    { "ru": "повар (человек) — как отличить от cooker?", "en": "cook = человек; cooker = плита" },
    { "ru": "тенёк (прохлада) — как отличить от shadow?", "en": "shade = прохлада/тень; shadow = форма тени от предмета" },
    { "ru": "еда вообще — как отличить от meal?", "en": "food = еда вообще; meal = приём пищи (завтрак/обед)" },
    { "ru": "дорога — как отличить от street, way, path?", "en": "road = дорога; street = улица; way = путь; path = тропа" }
  ]
}
